{
  "id": "chalkboard",
  "name": "Artisan Chalkboard",
  "description": "深みのあるスレートグリーンを背景に、ぬくもりのある黄白色（アイボリー）・セージグリーン・ブルーを配した黒板アート風テーマ。アンティークなチョークの質感をイメージした黄白色の文字が、カフェのような落ち着いた大人の空間を演出します。",

  "colors": {
    "background": "1A2624",
    "surface": "253532",
    "primary": "96ABA3",
    "secondary": "87CEEB",
    "text": "FFFDF0",
    "textMuted": "EAEADA",
    "border": "E0E0E0",
    "highlight": "FFF3A0"
  },

  "typography": {
    "fontTitle": "Chalkboard SE, Segoe Print, Ink Free, Meiryo",
    "fontBody": "Meiryo",
    "sizeTitleLarge": 42,
    "sizeTitleMedium": 28,
    "sizeBody": 18,
    "sizeSmall": 12
  },

  "shapes": {
    "style": "chalky",
    "cornerRadius": 0.02,
    "borderWidth": 1.5,
    "borderDash": "dash",
    "borderTransparency": 40,
    "decorations": "none",
    "shadow": {
      "enabled": false,
      "type": "outer",
      "color": "000000",
      "blur": 0,
      "offset": 0,
      "angle": 135,
      "opacity": 0
    }
  },

  "layout": {
    "margin": 0.5,
    "gutterV": 0.3,
    "gutterH": 0.4,
    "accentBarWidth": 0.1,
    "headerStyle": "none"
  },

  "chart": {
    "colors": ["96ABA3", "87CEEB", "FFBBDD", "FFF3A0", "98FB98", "FFDAB9"],
    "gridStyle": "subtle",
    "roundedCorners": false
  },

  "slideTypes": {
    "available": ["title", "overview", "comparison", "data", "flow"]
  },

  "tone": {
    "keywords": ["知性", "カフェ", "温もり", "手仕事", "プレミアム", "黒板", "高視認性", "セージグリーン", "アイボリー"],
    "formality": "casual",
    "industry": ["education", "food", "general", "creative"]
  }
}
